client_lib/__init__.py
client_lib/mine_task.py
mine_task-1.2.0.dist-info/LICENSE
mine_task-1.2.0.dist-info/METADATA
mine_task-1.2.0.dist-info/WHEEL
mine_task-1.2.0.dist-info/top_level.txt
mine_task-1.2.0.dist-info/RECORD
