Metadata-Version: 2.1
Name: mine_task
Version: 1.2.0
Summary: A client library for interacting with the task server.
Author-email: Andy Jin <2358155969@qq.com>
Requires-Python: >=3.8
License-File: LICENSE
Requires-Dist: requests>=2.0.0
